flask_htmldoom.py
Flask_Htmldoom-0.2.1.dist-info/LICENSE
Flask_Htmldoom-0.2.1.dist-info/METADATA
Flask_Htmldoom-0.2.1.dist-info/WHEEL
Flask_Htmldoom-0.2.1.dist-info/top_level.txt
Flask_Htmldoom-0.2.1.dist-info/RECORD
