Metadata-Version: 2.1
Name: Flask-Htmldoom
Version: 0.2.1
Summary: htmldoom integration for Flask
Home-page: https://github.com/sayanarijit/flask-htmldoom
Author: Arijit Basu
Author-email: sayanarijit@gmail.com
License: MIT
Keywords: html rendering for flask
Platform: Any
Classifier: Development Status :: 3 - Alpha
Classifier: Intended Audience :: Developers
Classifier: Intended Audience :: Information Technology
Classifier: Intended Audience :: Other Audience
Classifier: License :: OSI Approved :: MIT License
Classifier: Natural Language :: English
Classifier: Programming Language :: Python :: 3.6
Classifier: Programming Language :: Python :: 3.7
Classifier: Topic :: Utilities
Classifier: Topic :: Software Development
Classifier: Operating System :: MacOS
Classifier: Operating System :: Unix
Classifier: Operating System :: POSIX
Classifier: Operating System :: Microsoft
Classifier: Topic :: Internet :: WWW/HTTP :: Dynamic Content
Classifier: Topic :: Software Development :: Libraries :: Python Modules
Provides-Extra: testing
Provides-Extra: dev
